README.rst
setup.cfg
setup.py
gtsrvd/__init__.py
gtsrvd/app.py
gtsrvd/aws.py
gtsrvd/cli.py
gtsrvd/nginx.py
gtsrvd.egg-info/PKG-INFO
gtsrvd.egg-info/SOURCES.txt
gtsrvd.egg-info/dependency_links.txt
gtsrvd.egg-info/entry_points.txt
gtsrvd.egg-info/requires.txt
gtsrvd.egg-info/top_level.txt
gtsrvd.egg-info/zip-safe
tests/__init__.py
tests/test_app.py
tests/test_aws.py
tests/test_cli.py
tests/test_nginx.py